jaqalpaw/__init__.py
jaqalpaw/_cli.py
jaqalpaw/_import.py
jaqalpaw/bytecode/__init__.py
jaqalpaw/bytecode/binary_conversion.py
jaqalpaw/bytecode/encoding_parameters.py
jaqalpaw/bytecode/lut_programming.py
jaqalpaw/bytecode/pulse_binarization.py
jaqalpaw/bytecode/spline_mapping.py
jaqalpaw/compiler/__init__.py
jaqalpaw/compiler/jaqal_compiler.py
jaqalpaw/compiler/time_ordering.py
jaqalpaw/emulator/__init__.py
jaqalpaw/emulator/arbiters.py
jaqalpaw/emulator/byte_decoding.py
jaqalpaw/emulator/firmware_emulator.py
jaqalpaw/emulator/pdq_spline.py
jaqalpaw/emulator/uram.py
jaqalpaw/ir/__init__.py
jaqalpaw/ir/ast_utilities.py
jaqalpaw/ir/circuit_constructor.py
jaqalpaw/ir/circuit_constructor_visitor.py
jaqalpaw/ir/gate_slice.py
jaqalpaw/ir/padding.py
jaqalpaw/ir/pulse_data.py
jaqalpaw/utilities/__init__.py
jaqalpaw/utilities/datatypes.py
jaqalpaw/utilities/exceptions.py
jaqalpaw/utilities/helper_functions.py
jaqalpaw/utilities/parameters.py
jaqalpaw-1.3.0.data/data/share/jaqalpaw/examples/test_sk1.jaqal
jaqalpaw-1.3.0.data/data/share/jaqalpaw/examples/test_sk1.wvf
jaqalpaw-1.3.0.data/data/share/jaqalpaw/examples/test_std.jaqal
jaqalpaw-1.3.0.data/data/share/jaqalpaw/examples/test_std.wvf
jaqalpaw-1.3.0.data/data/share/jaqalpaw/examples/DocumentationSamples/ex14.jaqal
jaqalpaw-1.3.0.data/data/share/jaqalpaw/examples/DocumentationSamples/ex14.py
jaqalpaw-1.3.0.data/data/share/jaqalpaw/examples/DocumentationSamples/ex14.wvf
jaqalpaw-1.3.0.data/data/share/jaqalpaw/examples/DocumentationSamples/ex3.jaqal
jaqalpaw-1.3.0.data/data/share/jaqalpaw/examples/DocumentationSamples/ex3.py
jaqalpaw-1.3.0.data/data/share/jaqalpaw/examples/DocumentationSamples/ex3.wvf
jaqalpaw-1.3.0.data/data/share/jaqalpaw/examples/DocumentationSamples/ex4.jaqal
jaqalpaw-1.3.0.data/data/share/jaqalpaw/examples/DocumentationSamples/ex4.py
jaqalpaw-1.3.0.data/data/share/jaqalpaw/examples/DocumentationSamples/ex4.wvf
jaqalpaw-1.3.0.data/data/share/jaqalpaw/examples/DocumentationSamples/examples_iii_a.jaqal
jaqalpaw-1.3.0.dist-info/licenses/LICENSE
jaqalpaw-1.3.0.dist-info/licenses/NOTICE
jaqalpaw-1.3.0.dist-info/METADATA
jaqalpaw-1.3.0.dist-info/WHEEL
jaqalpaw-1.3.0.dist-info/entry_points.txt
jaqalpaw-1.3.0.dist-info/top_level.txt
jaqalpaw-1.3.0.dist-info/RECORD
